<?xml version="1.0" encoding="UTF-8"?>
<config xmlns="http://www.knime.org/2008/09/XMLConfig" xmlns:xsi="http://www.w3.org/2001/XMLSchema-instance" xsi:schemaLocation="http://www.knime.org/2008/09/XMLConfig http://www.knime.org/XMLConfig_2008_09.xsd" key="spec.xml">
<entry key="spec_name" type="xstring" value="default"/>
<entry key="number_columns" type="xint" value="8"/>
<config key="column_spec_0">
<entry key="column_name" type="xstring" value="Restaurant Name"/>
<config key="element_names">
<entry key="array-size" type="xint" value="0"/>
</config>
<config key="column_type">
<entry key="cell_class" type="xstring" value="org.knime.core.data.def.StringCell"/>
</config>
<config key="column_domain"/>
<config key="column_properties"/>
<config key="meta_data"/>
</config>
<config key="column_spec_1">
<entry key="column_name" type="xstring" value="Zip Code"/>
<config key="element_names">
<entry key="array-size" type="xint" value="0"/>
</config>
<config key="column_type">
<entry key="cell_class" type="xstring" value="org.knime.core.data.def.StringCell"/>
</config>
<config key="column_domain">
<config key="possible_values">
<entry key="array-size" type="xint" value="58"/>
<config key="0">
<entry key="datacell" type="xstring" value="org.knime.core.data.def.StringCell"/>
<config key="org.knime.core.data.def.StringCell">
<entry key="StringCell" type="xstring" value="78702"/>
</config>
</config>
<config key="1">
<entry key="datacell" type="xstring" value="org.knime.core.data.def.StringCell"/>
<config key="org.knime.core.data.def.StringCell">
<entry key="StringCell" type="xstring" value="78701"/>
</config>
</config>
<config key="2">
<entry key="datacell" type="xstring" value="org.knime.core.data.def.StringCell"/>
<config key="org.knime.core.data.def.StringCell">
<entry key="StringCell" type="xstring" value="78729"/>
</config>
</config>
<config key="3">
<entry key="datacell" type="xstring" value="org.knime.core.data.def.StringCell"/>
<config key="org.knime.core.data.def.StringCell">
<entry key="StringCell" type="xstring" value="78704"/>
</config>
</config>
<config key="4">
<entry key="datacell" type="xstring" value="org.knime.core.data.def.StringCell"/>
<config key="org.knime.core.data.def.StringCell">
<entry key="StringCell" type="xstring" value="78751"/>
</config>
</config>
<config key="5">
<entry key="datacell" type="xstring" value="org.knime.core.data.def.StringCell"/>
<config key="org.knime.core.data.def.StringCell">
<entry key="StringCell" type="xstring" value="78705"/>
</config>
</config>
<config key="6">
<entry key="datacell" type="xstring" value="org.knime.core.data.def.StringCell"/>
<config key="org.knime.core.data.def.StringCell">
<entry key="StringCell" type="xstring" value="78703"/>
</config>
</config>
<config key="7">
<entry key="datacell" type="xstring" value="org.knime.core.data.def.StringCell"/>
<config key="org.knime.core.data.def.StringCell">
<entry key="StringCell" type="xstring" value="78737"/>
</config>
</config>
<config key="8">
<entry key="datacell" type="xstring" value="org.knime.core.data.def.StringCell"/>
<config key="org.knime.core.data.def.StringCell">
<entry key="StringCell" type="xstring" value="78731"/>
</config>
</config>
<config key="9">
<entry key="datacell" type="xstring" value="org.knime.core.data.def.StringCell"/>
<config key="org.knime.core.data.def.StringCell">
<entry key="StringCell" type="xstring" value="78746"/>
</config>
</config>
<config key="10">
<entry key="datacell" type="xstring" value="org.knime.core.data.def.StringCell"/>
<config key="org.knime.core.data.def.StringCell">
<entry key="StringCell" type="xstring" value="78726"/>
</config>
</config>
<config key="11">
<entry key="datacell" type="xstring" value="org.knime.core.data.def.StringCell"/>
<config key="org.knime.core.data.def.StringCell">
<entry key="StringCell" type="xstring" value="78745"/>
</config>
</config>
<config key="12">
<entry key="datacell" type="xstring" value="org.knime.core.data.def.StringCell"/>
<config key="org.knime.core.data.def.StringCell">
<entry key="StringCell" type="xstring" value="78756"/>
</config>
</config>
<config key="13">
<entry key="datacell" type="xstring" value="org.knime.core.data.def.StringCell"/>
<config key="org.knime.core.data.def.StringCell">
<entry key="StringCell" type="xstring" value="78734"/>
</config>
</config>
<config key="14">
<entry key="datacell" type="xstring" value="org.knime.core.data.def.StringCell"/>
<config key="org.knime.core.data.def.StringCell">
<entry key="StringCell" type="xstring" value="78652"/>
</config>
</config>
<config key="15">
<entry key="datacell" type="xstring" value="org.knime.core.data.def.StringCell"/>
<config key="org.knime.core.data.def.StringCell">
<entry key="StringCell" type="xstring" value="78741"/>
</config>
</config>
<config key="16">
<entry key="datacell" type="xstring" value="org.knime.core.data.def.StringCell"/>
<config key="org.knime.core.data.def.StringCell">
<entry key="StringCell" type="xstring" value="78757"/>
</config>
</config>
<config key="17">
<entry key="datacell" type="xstring" value="org.knime.core.data.def.StringCell"/>
<config key="org.knime.core.data.def.StringCell">
<entry key="StringCell" type="xstring" value="78717"/>
</config>
</config>
<config key="18">
<entry key="datacell" type="xstring" value="org.knime.core.data.def.StringCell"/>
<config key="org.knime.core.data.def.StringCell">
<entry key="StringCell" type="xstring" value="78748"/>
</config>
</config>
<config key="19">
<entry key="datacell" type="xstring" value="org.knime.core.data.def.StringCell"/>
<config key="org.knime.core.data.def.StringCell">
<entry key="StringCell" type="xstring" value="78744"/>
</config>
</config>
<config key="20">
<entry key="datacell" type="xstring" value="org.knime.core.data.def.StringCell"/>
<config key="org.knime.core.data.def.StringCell">
<entry key="StringCell" type="xstring" value="78660"/>
</config>
</config>
<config key="21">
<entry key="datacell" type="xstring" value="org.knime.core.data.def.StringCell"/>
<config key="org.knime.core.data.def.StringCell">
<entry key="StringCell" type="xstring" value="78758"/>
</config>
</config>
<config key="22">
<entry key="datacell" type="xstring" value="org.knime.core.data.def.StringCell"/>
<config key="org.knime.core.data.def.StringCell">
<entry key="StringCell" type="xstring" value="78753"/>
</config>
</config>
<config key="23">
<entry key="datacell" type="xstring" value="org.knime.core.data.def.StringCell"/>
<config key="org.knime.core.data.def.StringCell">
<entry key="StringCell" type="xstring" value="78754"/>
</config>
</config>
<config key="24">
<entry key="datacell" type="xstring" value="org.knime.core.data.def.StringCell"/>
<config key="org.knime.core.data.def.StringCell">
<entry key="StringCell" type="xstring" value="78727"/>
</config>
</config>
<config key="25">
<entry key="datacell" type="xstring" value="org.knime.core.data.def.StringCell"/>
<config key="org.knime.core.data.def.StringCell">
<entry key="StringCell" type="xstring" value="78759"/>
</config>
</config>
<config key="26">
<entry key="datacell" type="xstring" value="org.knime.core.data.def.StringCell"/>
<config key="org.knime.core.data.def.StringCell">
<entry key="StringCell" type="xstring" value="78732"/>
</config>
</config>
<config key="27">
<entry key="datacell" type="xstring" value="org.knime.core.data.def.StringCell"/>
<config key="org.knime.core.data.def.StringCell">
<entry key="StringCell" type="xstring" value="78749"/>
</config>
</config>
<config key="28">
<entry key="datacell" type="xstring" value="org.knime.core.data.def.StringCell"/>
<config key="org.knime.core.data.def.StringCell">
<entry key="StringCell" type="xstring" value="78723"/>
</config>
</config>
<config key="29">
<entry key="datacell" type="xstring" value="org.knime.core.data.def.StringCell"/>
<config key="org.knime.core.data.def.StringCell">
<entry key="StringCell" type="xstring" value="78752"/>
</config>
</config>
<config key="30">
<entry key="datacell" type="xstring" value="org.knime.core.data.def.StringCell"/>
<config key="org.knime.core.data.def.StringCell">
<entry key="StringCell" type="xstring" value="78722"/>
</config>
</config>
<config key="31">
<entry key="datacell" type="xstring" value="org.knime.core.data.def.StringCell"/>
<config key="org.knime.core.data.def.StringCell">
<entry key="StringCell" type="xstring" value="78725"/>
</config>
</config>
<config key="32">
<entry key="datacell" type="xstring" value="org.knime.core.data.def.StringCell"/>
<config key="org.knime.core.data.def.StringCell">
<entry key="StringCell" type="xstring" value="78653"/>
</config>
</config>
<config key="33">
<entry key="datacell" type="xstring" value="org.knime.core.data.def.StringCell"/>
<config key="org.knime.core.data.def.StringCell">
<entry key="StringCell" type="xstring" value="78719"/>
</config>
</config>
<config key="34">
<entry key="datacell" type="xstring" value="org.knime.core.data.def.StringCell"/>
<config key="org.knime.core.data.def.StringCell">
<entry key="StringCell" type="xstring" value="78743"/>
</config>
</config>
<config key="35">
<entry key="datacell" type="xstring" value="org.knime.core.data.def.StringCell"/>
<config key="org.knime.core.data.def.StringCell">
<entry key="StringCell" type="xstring" value="78613"/>
</config>
</config>
<config key="36">
<entry key="datacell" type="xstring" value="org.knime.core.data.def.StringCell"/>
<config key="org.knime.core.data.def.StringCell">
<entry key="StringCell" type="xstring" value="78739"/>
</config>
</config>
<config key="37">
<entry key="datacell" type="xstring" value="org.knime.core.data.def.StringCell"/>
<config key="org.knime.core.data.def.StringCell">
<entry key="StringCell" type="xstring" value="78750"/>
</config>
</config>
<config key="38">
<entry key="datacell" type="xstring" value="org.knime.core.data.def.StringCell"/>
<config key="org.knime.core.data.def.StringCell">
<entry key="StringCell" type="xstring" value="78721"/>
</config>
</config>
<config key="39">
<entry key="datacell" type="xstring" value="org.knime.core.data.def.StringCell"/>
<config key="org.knime.core.data.def.StringCell">
<entry key="StringCell" type="xstring" value="78669"/>
</config>
</config>
<config key="40">
<entry key="datacell" type="xstring" value="org.knime.core.data.def.StringCell"/>
<config key="org.knime.core.data.def.StringCell">
<entry key="StringCell" type="xstring" value="78617"/>
</config>
</config>
<config key="41">
<entry key="datacell" type="xstring" value="org.knime.core.data.def.StringCell"/>
<config key="org.knime.core.data.def.StringCell">
<entry key="StringCell" type="xstring" value="78735"/>
</config>
</config>
<config key="42">
<entry key="datacell" type="xstring" value="org.knime.core.data.def.StringCell"/>
<config key="org.knime.core.data.def.StringCell">
<entry key="StringCell" type="xstring" value="78728"/>
</config>
</config>
<config key="43">
<entry key="datacell" type="xstring" value="org.knime.core.data.def.StringCell"/>
<config key="org.knime.core.data.def.StringCell">
<entry key="StringCell" type="xstring" value="78610"/>
</config>
</config>
<config key="44">
<entry key="datacell" type="xstring" value="org.knime.core.data.def.StringCell"/>
<config key="org.knime.core.data.def.StringCell">
<entry key="StringCell" type="xstring" value="78733"/>
</config>
</config>
<config key="45">
<entry key="datacell" type="xstring" value="org.knime.core.data.def.StringCell"/>
<config key="org.knime.core.data.def.StringCell">
<entry key="StringCell" type="xstring" value="78654"/>
</config>
</config>
<config key="46">
<entry key="datacell" type="xstring" value="org.knime.core.data.def.StringCell"/>
<config key="org.knime.core.data.def.StringCell">
<entry key="StringCell" type="xstring" value="78724"/>
</config>
</config>
<config key="47">
<entry key="datacell" type="xstring" value="org.knime.core.data.def.StringCell"/>
<config key="org.knime.core.data.def.StringCell">
<entry key="StringCell" type="xstring" value="78738"/>
</config>
</config>
<config key="48">
<entry key="datacell" type="xstring" value="org.knime.core.data.def.StringCell"/>
<config key="org.knime.core.data.def.StringCell">
<entry key="StringCell" type="xstring" value="78736"/>
</config>
</config>
<config key="49">
<entry key="datacell" type="xstring" value="org.knime.core.data.def.StringCell"/>
<config key="org.knime.core.data.def.StringCell">
<entry key="StringCell" type="xstring" value="78730"/>
</config>
</config>
<config key="50">
<entry key="datacell" type="xstring" value="org.knime.core.data.def.StringCell"/>
<config key="org.knime.core.data.def.StringCell">
<entry key="StringCell" type="xstring" value="78747"/>
</config>
</config>
<config key="51">
<entry key="datacell" type="xstring" value="org.knime.core.data.def.StringCell"/>
<config key="org.knime.core.data.def.StringCell">
<entry key="StringCell" type="xstring" value="78641"/>
</config>
</config>
<config key="52">
<entry key="datacell" type="xstring" value="org.knime.core.data.def.StringCell"/>
<config key="org.knime.core.data.def.StringCell">
<entry key="StringCell" type="xstring" value="78620"/>
</config>
</config>
<config key="53">
<entry key="datacell" type="xstring" value="org.knime.core.data.def.StringCell"/>
<config key="org.knime.core.data.def.StringCell">
<entry key="StringCell" type="xstring" value="78612"/>
</config>
</config>
<config key="54">
<entry key="datacell" type="xstring" value="org.knime.core.data.def.StringCell"/>
<config key="org.knime.core.data.def.StringCell">
<entry key="StringCell" type="xstring" value="Hwy 290 E Austin 78723 Juriscode: 01"/>
</config>
</config>
<config key="55">
<entry key="datacell" type="xstring" value="org.knime.core.data.def.StringCell"/>
<config key="org.knime.core.data.def.StringCell">
<entry key="StringCell" type="xstring" value="78615"/>
</config>
</config>
<config key="56">
<entry key="datacell" type="xstring" value="org.knime.core.data.def.StringCell"/>
<config key="org.knime.core.data.def.StringCell">
<entry key="StringCell" type="xstring" value="78742"/>
</config>
</config>
<config key="57">
<entry key="datacell" type="xstring" value="org.knime.core.data.def.StringCell"/>
<config key="org.knime.core.data.def.StringCell">
<entry key="StringCell" type="xstring" value="78621"/>
</config>
</config>
</config>
</config>
<config key="column_properties"/>
<config key="meta_data"/>
</config>
<config key="column_spec_2">
<entry key="column_name" type="xstring" value="Inspection Date"/>
<config key="element_names">
<entry key="array-size" type="xint" value="0"/>
</config>
<config key="column_type">
<entry key="cell_class" type="xstring" value="org.knime.core.data.time.localdate.LocalDateCell"/>
</config>
<config key="column_domain">
<config key="lower_bound">
<entry key="datacell" type="xstring" value="org.knime.core.data.time.localdate.LocalDateCell"/>
<entry key="datacell_serialized" type="xstring" value="rO0ABXNyADBvcmcua25pbWUuY29yZS5kYXRhLnRpbWUubG9jYWxkYXRlLkxvY2FsRGF0ZUNlbGyMRXN6y/zSRAIAAUwAC21fbG9jYWxEYXRldAAVTGphdmEvdGltZS9Mb2NhbERhdGU7eHIAHG9yZy5rbmltZS5jb3JlLmRhdGEuRGF0YUNlbGxm6eiJVomygAIAAHhwc3IADWphdmEudGltZS5TZXKVXYS6GyJIsgwAAHhwdwcDAAAH3QQIeA=="/>
</config>
<config key="upper_bound">
<entry key="datacell" type="xstring" value="org.knime.core.data.time.localdate.LocalDateCell"/>
<entry key="datacell_serialized" type="xstring" value="rO0ABXNyADBvcmcua25pbWUuY29yZS5kYXRhLnRpbWUubG9jYWxkYXRlLkxvY2FsRGF0ZUNlbGyMRXN6y/zSRAIAAUwAC21fbG9jYWxEYXRldAAVTGphdmEvdGltZS9Mb2NhbERhdGU7eHIAHG9yZy5rbmltZS5jb3JlLmRhdGEuRGF0YUNlbGxm6eiJVomygAIAAHhwc3IADWphdmEudGltZS5TZXKVXYS6GyJIsgwAAHhwdwcDAAAH4AMTeA=="/>
</config>
</config>
<config key="column_properties"/>
<config key="meta_data"/>
</config>
<config key="column_spec_3">
<entry key="column_name" type="xstring" value="Score"/>
<config key="element_names">
<entry key="array-size" type="xint" value="0"/>
</config>
<config key="column_type">
<entry key="cell_class" type="xstring" value="org.knime.core.data.def.IntCell"/>
</config>
<config key="column_domain">
<config key="lower_bound">
<entry key="datacell" type="xstring" value="org.knime.core.data.def.IntCell"/>
<config key="org.knime.core.data.def.IntCell">
<entry key="IntCell" type="xint" value="36"/>
</config>
</config>
<config key="upper_bound">
<entry key="datacell" type="xstring" value="org.knime.core.data.def.IntCell"/>
<config key="org.knime.core.data.def.IntCell">
<entry key="IntCell" type="xint" value="100"/>
</config>
</config>
</config>
<config key="column_properties"/>
<config key="color_handler">
<entry key="color_model_class" type="xstring" value="org.knime.core.data.property.ColorModelRange"/>
<config key="color_model">
<entry key="lower_value" type="xdouble" value="36.0"/>
<entry key="upper_value" type="xdouble" value="100.0"/>
<config key="lower_color">
<entry key="array-size" type="xint" value="4"/>
<entry key="0" type="xint" value="255"/>
<entry key="1" type="xint" value="0"/>
<entry key="2" type="xint" value="0"/>
<entry key="3" type="xint" value="255"/>
</config>
<config key="upper_color">
<entry key="array-size" type="xint" value="4"/>
<entry key="0" type="xint" value="0"/>
<entry key="1" type="xint" value="0"/>
<entry key="2" type="xint" value="255"/>
<entry key="3" type="xint" value="255"/>
</config>
</config>
</config>
<config key="meta_data"/>
</config>
<config key="column_spec_4">
<entry key="column_name" type="xstring" value="Address"/>
<config key="element_names">
<entry key="array-size" type="xint" value="0"/>
</config>
<config key="column_type">
<entry key="cell_class" type="xstring" value="org.knime.core.data.def.StringCell"/>
</config>
<config key="column_domain"/>
<config key="column_properties"/>
<config key="meta_data"/>
</config>
<config key="column_spec_5">
<entry key="column_name" type="xstring" value="Facility ID"/>
<config key="element_names">
<entry key="array-size" type="xint" value="0"/>
</config>
<config key="column_type">
<entry key="cell_class" type="xstring" value="org.knime.core.data.def.IntCell"/>
</config>
<config key="column_domain">
<config key="lower_bound">
<entry key="datacell" type="xstring" value="org.knime.core.data.def.IntCell"/>
<config key="org.knime.core.data.def.IntCell">
<entry key="IntCell" type="xint" value="2800004"/>
</config>
</config>
<config key="upper_bound">
<entry key="datacell" type="xstring" value="org.knime.core.data.def.IntCell"/>
<config key="org.knime.core.data.def.IntCell">
<entry key="IntCell" type="xint" value="11412662"/>
</config>
</config>
</config>
<config key="column_properties"/>
<config key="meta_data"/>
</config>
<config key="column_spec_6">
<entry key="column_name" type="xstring" value="Process Description"/>
<config key="element_names">
<entry key="array-size" type="xint" value="0"/>
</config>
<config key="column_type">
<entry key="cell_class" type="xstring" value="org.knime.core.data.def.StringCell"/>
</config>
<config key="column_domain">
<config key="possible_values">
<entry key="array-size" type="xint" value="4"/>
<config key="0">
<entry key="datacell" type="xstring" value="org.knime.core.data.def.StringCell"/>
<config key="org.knime.core.data.def.StringCell">
<entry key="StringCell" type="xstring" value="Routine Inspection"/>
</config>
</config>
<config key="1">
<entry key="datacell" type="xstring" value="org.knime.core.data.def.StringCell"/>
<config key="org.knime.core.data.def.StringCell">
<entry key="StringCell" type="xstring" value="2nd Follow Up to 50 - 69"/>
</config>
</config>
<config key="2">
<entry key="datacell" type="xstring" value="org.knime.core.data.def.StringCell"/>
<config key="org.knime.core.data.def.StringCell">
<entry key="StringCell" type="xstring" value="1st Follow Up to Routine of 50 - 69"/>
</config>
</config>
<config key="3">
<entry key="datacell" type="xstring" value="org.knime.core.data.def.StringCell"/>
<config key="org.knime.core.data.def.StringCell">
<entry key="StringCell" type="xstring" value="1st Follow Up to Routine of 49 or less"/>
</config>
</config>
</config>
</config>
<config key="column_properties"/>
<config key="meta_data"/>
</config>
<config key="column_spec_7">
<entry key="column_name" type="xstring" value="Selected (Scatter Plot)"/>
<config key="element_names">
<entry key="array-size" type="xint" value="0"/>
</config>
<config key="column_type">
<entry key="cell_class" type="xstring" value="org.knime.core.data.def.BooleanCell"/>
</config>
<config key="column_domain">
<config key="lower_bound">
<entry key="datacell" type="xstring" value="org.knime.core.data.def.BooleanCell"/>
<config key="org.knime.core.data.def.BooleanCell">
<entry key="BooleanCell" type="xboolean" value="false"/>
</config>
</config>
<config key="upper_bound">
<entry key="datacell" type="xstring" value="org.knime.core.data.def.BooleanCell"/>
<config key="org.knime.core.data.def.BooleanCell">
<entry key="BooleanCell" type="xboolean" value="false"/>
</config>
</config>
<config key="possible_values">
<entry key="array-size" type="xint" value="1"/>
<config key="0">
<entry key="datacell" type="xstring" value="org.knime.core.data.def.BooleanCell"/>
<config key="org.knime.core.data.def.BooleanCell">
<entry key="BooleanCell" type="xboolean" value="false"/>
</config>
</config>
</config>
</config>
<config key="column_properties"/>
<config key="meta_data"/>
</config>
</config>
